{
    "terminals": [
        "$",
        "(",
        ")",
        "*",
        "+",
        ",",
        "-",
        "/",
        ":",
        ";",
        "<",
        "=",
        "[",
        "]",
        "{",
        "}",
        "NUM",
        "ID",
        "int",
        "void",
        "break",
        "if",
        "endif",
        "else",
        "while",
        "return",
        "switch",
        "case",
        "default",
        "=="
    ],
    "non_terminals": [
        "$accept",
        "program",
        "declaration_list",
        "declaration",
        "var_declaration",
        "type_specifier",
        "fun_declaration",
        "params",
        "param_list",
        "param",
        "compound_stmt",
        "local_declarations",
        "statement_list",
        "statement",
        "expression_stmt",
        "selection_stmt",
        "iteration_stmt",
        "return_stmt",
        "switch_stmt",
        "case_stmts",
        "case_stmt",
        "default_stmt",
        "expression",
        "var",
        "simple_expression",
        "relop",
        "additive_expression",
        "addop",
        "term",
        "mulop",
        "factor",
        "call",
        "add_args",
        "print",
        "end_args",
        "args",
        "arg_list",
        "save",
        "jpf_save",
        "label",
        "switch",
        "pid",
        "declare_id",
        "end_declare",
        "op",
        "num"
    ],
    "first": {
        "$accept": [
            "void",
            "int"
        ],
        "program": [
            "void",
            "int"
        ],
        "declaration_list": [
            "void",
            "int"
        ],
        "declaration": [
            "void",
            "int"
        ],
        "var_declaration": [
            "void",
            "int"
        ],
        "type_specifier": [
            "void",
            "int"
        ],
        "fun_declaration": [
            "void",
            "int"
        ],
        "params": [
            "void",
            "int"
        ],
        "param_list": [
            "void",
            "int"
        ],
        "param": [
            "void",
            "int"
        ],
        "compound_stmt": [
            "{"
        ],
        "local_declarations": [
            "void",
            "int"
        ],
        "statement_list": [
            "NUM",
            ";",
            "(",
            "return",
            "while",
            "{",
            "break",
            "ID",
            "if",
            "switch"
        ],
        "statement": [
            "while",
            "NUM",
            ";",
            "{",
            "break",
            "(",
            "ID",
            "if",
            "switch",
            "return"
        ],
        "expression_stmt": [
            "(",
            "NUM",
            "break",
            "ID",
            ";"
        ],
        "selection_stmt": [
            "if"
        ],
        "iteration_stmt": [
            "while"
        ],
        "return_stmt": [
            "return"
        ],
        "switch_stmt": [
            "switch",
            "("
        ],
        "case_stmts": [
            "case"
        ],
        "case_stmt": [
            "case"
        ],
        "default_stmt": [
            "default"
        ],
        "expression": [
            "NUM",
            "ID",
            "("
        ],
        "var": [
            "ID"
        ],
        "simple_expression": [
            "NUM",
            "ID",
            "("
        ],
        "relop": [
            "<",
            "=="
        ],
        "additive_expression": [
            "NUM",
            "ID",
            "("
        ],
        "addop": [
            "+",
            "-"
        ],
        "term": [
            "NUM",
            "ID",
            "("
        ],
        "mulop": [
            "/",
            "*"
        ],
        "factor": [
            "NUM",
            "ID",
            "("
        ],
        "call": [
            "ID"
        ],
        "add_args": [],
        "print": [],
        "end_args": [],
        "args": [
            "NUM",
            "ID",
            "("
        ],
        "arg_list": [
            "NUM",
            "ID",
            "("
        ],
        "save": [],
        "jpf_save": [],
        "label": [],
        "switch": [
            "switch"
        ],
        "pid": [],
        "declare_id": [],
        "end_declare": [],
        "op": [],
        "num": [],
        "$": [
            "$"
        ],
        "(": [
            "("
        ],
        ")": [
            ")"
        ],
        "*": [
            "*"
        ],
        "+": [
            "+"
        ],
        ",": [
            ","
        ],
        "-": [
            "-"
        ],
        "/": [
            "/"
        ],
        ":": [
            ":"
        ],
        ";": [
            ";"
        ],
        "<": [
            "<"
        ],
        "=": [
            "="
        ],
        "[": [
            "["
        ],
        "]": [
            "]"
        ],
        "{": [
            "{"
        ],
        "}": [
            "}"
        ],
        "NUM": [
            "NUM"
        ],
        "ID": [
            "ID"
        ],
        "int": [
            "int"
        ],
        "void": [
            "void"
        ],
        "break": [
            "break"
        ],
        "if": [
            "if"
        ],
        "endif": [
            "endif"
        ],
        "else": [
            "else"
        ],
        "while": [
            "while"
        ],
        "return": [
            "return"
        ],
        "case": [
            "case"
        ],
        "default": [
            "default"
        ],
        "==": [
            "=="
        ]
    },
    "follow": {
        "$accept": [],
        "program": [
            "$"
        ],
        "declaration_list": [
            "void",
            "int",
            "$"
        ],
        "declaration": [
            "void",
            "int",
            "$"
        ],
        "var_declaration": [
            "NUM",
            "$",
            ";",
            "(",
            "return",
            "void",
            "int",
            "while",
            "{",
            "}",
            "break",
            "ID",
            "if",
            "switch"
        ],
        "type_specifier": [
            "ID"
        ],
        "fun_declaration": [
            "void",
            "int",
            "$"
        ],
        "params": [
            ")"
        ],
        "param_list": [
            ",",
            ")"
        ],
        "param": [
            ",",
            ")"
        ],
        "compound_stmt": [
            "NUM",
            "$",
            ";",
            "(",
            "return",
            "void",
            "int",
            "while",
            "else",
            "default",
            "{",
            "}",
            "endif",
            "break",
            "ID",
            "if",
            "switch",
            "case"
        ],
        "local_declarations": [
            "NUM",
            ";",
            "(",
            "return",
            "void",
            "int",
            "while",
            "{",
            "}",
            "break",
            "ID",
            "if",
            "switch"
        ],
        "statement_list": [
            "NUM",
            ";",
            "(",
            "return",
            "while",
            "default",
            "{",
            "}",
            "break",
            "ID",
            "if",
            "switch",
            "case"
        ],
        "statement": [
            "NUM",
            ";",
            "(",
            "return",
            "while",
            "else",
            "default",
            "{",
            "}",
            "endif",
            "break",
            "ID",
            "if",
            "switch",
            "case"
        ],
        "expression_stmt": [
            "NUM",
            ";",
            "(",
            "return",
            "while",
            "else",
            "default",
            "{",
            "}",
            "endif",
            "break",
            "ID",
            "if",
            "switch",
            "case"
        ],
        "selection_stmt": [
            "NUM",
            ";",
            "(",
            "return",
            "while",
            "else",
            "default",
            "{",
            "}",
            "endif",
            "break",
            "ID",
            "if",
            "switch",
            "case"
        ],
        "iteration_stmt": [
            "NUM",
            ";",
            "(",
            "return",
            "while",
            "else",
            "default",
            "{",
            "}",
            "endif",
            "break",
            "ID",
            "if",
            "switch",
            "case"
        ],
        "return_stmt": [
            "NUM",
            ";",
            "(",
            "return",
            "while",
            "else",
            "default",
            "{",
            "}",
            "endif",
            "break",
            "ID",
            "if",
            "switch",
            "case"
        ],
        "switch_stmt": [
            "NUM",
            ";",
            "(",
            "return",
            "while",
            "else",
            "default",
            "{",
            "}",
            "endif",
            "break",
            "ID",
            "if",
            "switch",
            "case"
        ],
        "case_stmts": [
            "}",
            "default",
            "case"
        ],
        "case_stmt": [
            "}",
            "default",
            "case"
        ],
        "default_stmt": [
            "}"
        ],
        "expression": [
            ")",
            "]",
            ",",
            ";"
        ],
        "var": [
            "+",
            ")",
            "-",
            ";",
            "<",
            "*",
            ",",
            "==",
            "=",
            "/",
            "]"
        ],
        "simple_expression": [
            ")",
            "]",
            ",",
            ";"
        ],
        "relop": [
            "NUM",
            "ID",
            "("
        ],
        "additive_expression": [
            "+",
            ")",
            "-",
            "<",
            ";",
            "]",
            ",",
            "=="
        ],
        "addop": [
            "NUM",
            "ID",
            "("
        ],
        "term": [
            "+",
            "*",
            ")",
            "-",
            "/",
            ";",
            "<",
            "]",
            ",",
            "=="
        ],
        "mulop": [
            "NUM",
            "ID",
            "("
        ],
        "factor": [
            "+",
            ")",
            "-",
            ";",
            "<",
            "*",
            ",",
            "==",
            "/",
            "]"
        ],
        "call": [
            "+",
            ")",
            "-",
            ";",
            "<",
            "*",
            ",",
            "==",
            "/",
            "]"
        ],
        "add_args": [
            ")",
            "NUM",
            "ID",
            "("
        ],
        "print": [
            "+",
            ")",
            "-",
            ";",
            "<",
            "*",
            ",",
            "==",
            "/",
            "]"
        ],
        "end_args": [
            "+",
            ")",
            "-",
            "<",
            ";",
            "*",
            ",",
            "==",
            "/",
            "]"
        ],
        "args": [
            ")"
        ],
        "arg_list": [
            ",",
            ")"
        ],
        "save": [
            "NUM",
            ";",
            ":",
            "(",
            "return",
            "while",
            "{",
            "break",
            "ID",
            "if",
            "switch"
        ],
        "jpf_save": [
            "NUM",
            ";",
            "(",
            "return",
            "while",
            "default",
            "{",
            "break",
            "ID",
            "if",
            "switch",
            "case"
        ],
        "label": [
            "("
        ],
        "switch": [
            "switch",
            "("
        ],
        "pid": [
            "ID"
        ],
        "declare_id": [
            "ID"
        ],
        "end_declare": [
            "{"
        ],
        "op": [
            "+",
            "-",
            "/",
            "*"
        ],
        "num": [
            "NUM"
        ]
    },
    "grammar": {
        "0": [
            "$accept",
            "->",
            "program",
            "$"
        ],
        "1": [
            "program",
            "->",
            "declaration_list"
        ],
        "2": [
            "declaration_list",
            "->",
            "declaration_list",
            "declaration"
        ],
        "3": [
            "declaration_list",
            "->",
            "declaration"
        ],
        "4": [
            "declaration",
            "->",
            "var_declaration"
        ],
        "5": [
            "declaration",
            "->",
            "fun_declaration"
        ],
        "6": [
            "var_declaration",
            "->",
            "type_specifier",
            "declare_id",
            "pid",
            "ID",
            ";"
        ],
        "7": [
            "var_declaration",
            "->",
            "type_specifier",
            "declare_id",
            "pid",
            "ID",
            "[",
            "NUM",
            "]",
            ";"
        ],
        "8": [
            "type_specifier",
            "->",
            "int"
        ],
        "9": [
            "type_specifier",
            "->",
            "void"
        ],
        "10": [
            "fun_declaration",
            "->",
            "type_specifier",
            "declare_id",
            "pid",
            "ID",
            "(",
            "params",
            ")",
            "end_declare",
            "compound_stmt"
        ],
        "11": [
            "params",
            "->",
            "param_list"
        ],
        "12": [
            "params",
            "->",
            "void"
        ],
        "13": [
            "param_list",
            "->",
            "param_list",
            ",",
            "param"
        ],
        "14": [
            "param_list",
            "->",
            "param"
        ],
        "15": [
            "param",
            "->",
            "type_specifier",
            "declare_id",
            "pid",
            "ID"
        ],
        "16": [
            "param",
            "->",
            "type_specifier",
            "declare_id",
            "pid",
            "ID",
            "[",
            "]"
        ],
        "17": [
            "compound_stmt",
            "->",
            "{",
            "local_declarations",
            "statement_list",
            "}"
        ],
        "18": [
            "local_declarations",
            "->",
            "local_declarations",
            "var_declaration"
        ],
        "19": [
            "local_declarations",
            "->",
            "epsilon"
        ],
        "20": [
            "statement_list",
            "->",
            "statement_list",
            "statement"
        ],
        "21": [
            "statement_list",
            "->",
            "epsilon"
        ],
        "22": [
            "statement",
            "->",
            "expression_stmt"
        ],
        "23": [
            "statement",
            "->",
            "compound_stmt"
        ],
        "24": [
            "statement",
            "->",
            "selection_stmt"
        ],
        "25": [
            "statement",
            "->",
            "iteration_stmt"
        ],
        "26": [
            "statement",
            "->",
            "return_stmt"
        ],
        "27": [
            "statement",
            "->",
            "switch_stmt"
        ],
        "28": [
            "expression_stmt",
            "->",
            "expression",
            ";"
        ],
        "29": [
            "expression_stmt",
            "->",
            "break",
            ";"
        ],
        "30": [
            "expression_stmt",
            "->",
            ";"
        ],
        "31": [
            "selection_stmt",
            "->",
            "if",
            "(",
            "expression",
            ")",
            "save",
            "statement",
            "endif"
        ],
        "32": [
            "selection_stmt",
            "->",
            "if",
            "(",
            "expression",
            ")",
            "save",
            "statement",
            "else",
            "jpf_save",
            "statement",
            "endif"
        ],
        "33": [
            "iteration_stmt",
            "->",
            "while",
            "label",
            "(",
            "expression",
            ")",
            "save",
            "statement"
        ],
        "34": [
            "return_stmt",
            "->",
            "return",
            ";"
        ],
        "35": [
            "return_stmt",
            "->",
            "return",
            "expression",
            ";"
        ],
        "36": [
            "switch_stmt",
            "->",
            "switch",
            "switch",
            "(",
            "expression",
            ")",
            "{",
            "case_stmts",
            "default_stmt",
            "}"
        ],
        "37": [
            "case_stmts",
            "->",
            "case_stmts",
            "case_stmt"
        ],
        "38": [
            "case_stmts",
            "->",
            "epsilon"
        ],
        "39": [
            "case_stmt",
            "->",
            "jpf_save",
            "case",
            "NUM",
            "save",
            ":",
            "statement_list"
        ],
        "40": [
            "default_stmt",
            "->",
            "jpf_save",
            "default",
            ":",
            "statement_list"
        ],
        "41": [
            "default_stmt",
            "->",
            "epsilon"
        ],
        "42": [
            "expression",
            "->",
            "var",
            "=",
            "expression"
        ],
        "43": [
            "expression",
            "->",
            "simple_expression"
        ],
        "44": [
            "var",
            "->",
            "declare_id",
            "pid",
            "ID"
        ],
        "45": [
            "var",
            "->",
            "declare_id",
            "pid",
            "ID",
            "[",
            "expression",
            "]"
        ],
        "46": [
            "simple_expression",
            "->",
            "additive_expression",
            "relop",
            "additive_expression"
        ],
        "47": [
            "simple_expression",
            "->",
            "additive_expression"
        ],
        "48": [
            "relop",
            "->",
            "<"
        ],
        "49": [
            "relop",
            "->",
            "=="
        ],
        "50": [
            "additive_expression",
            "->",
            "additive_expression",
            "addop",
            "term"
        ],
        "51": [
            "additive_expression",
            "->",
            "term"
        ],
        "52": [
            "addop",
            "->",
            "op",
            "+"
        ],
        "53": [
            "addop",
            "->",
            "op",
            "-"
        ],
        "54": [
            "term",
            "->",
            "term",
            "mulop",
            "factor"
        ],
        "55": [
            "term",
            "->",
            "factor"
        ],
        "56": [
            "mulop",
            "->",
            "op",
            "*"
        ],
        "57": [
            "mulop",
            "->",
            "op",
            "/"
        ],
        "58": [
            "factor",
            "->",
            "(",
            "expression",
            ")"
        ],
        "59": [
            "factor",
            "->",
            "var"
        ],
        "60": [
            "factor",
            "->",
            "call"
        ],
        "61": [
            "factor",
            "->",
            "num",
            "NUM"
        ],
        "62": [
            "call",
            "->",
            "declare_id",
            "pid",
            "ID",
            "(",
            "add_args",
            "args",
            ")",
            "end_args",
            "print"
        ],
        "63": [
            "add_args",
            "->",
            "epsilon"
        ],
        "64": [
            "print",
            "->",
            "epsilon"
        ],
        "65": [
            "end_args",
            "->",
            "epsilon"
        ],
        "66": [
            "args",
            "->",
            "arg_list"
        ],
        "67": [
            "args",
            "->",
            "epsilon"
        ],
        "68": [
            "arg_list",
            "->",
            "arg_list",
            ",",
            "expression"
        ],
        "69": [
            "arg_list",
            "->",
            "expression"
        ],
        "70": [
            "save",
            "->",
            "epsilon"
        ],
        "71": [
            "jpf_save",
            "->",
            "epsilon"
        ],
        "72": [
            "label",
            "->",
            "epsilon"
        ],
        "73": [
            "switch",
            "->",
            "epsilon"
        ],
        "74": [
            "pid",
            "->",
            "epsilon"
        ],
        "75": [
            "declare_id",
            "->",
            "epsilon"
        ],
        "76": [
            "end_declare",
            "->",
            "epsilon"
        ],
        "77": [
            "op",
            "->",
            "epsilon"
        ],
        "78": [
            "num",
            "->",
            "epsilon"
        ]
    },
    "parse_table": {
        "0": {
            "int": "shift_1",
            "void": "shift_2",
            "program": "goto_3",
            "declaration_list": "goto_4",
            "declaration": "goto_5",
            "var_declaration": "goto_6",
            "type_specifier": "goto_7",
            "fun_declaration": "goto_8"
        },
        "1": {
            "ID": "reduce_8"
        },
        "2": {
            "ID": "reduce_9"
        },
        "3": {
            "$": "shift_9"
        },
        "4": {
            "int": "shift_1",
            "void": "shift_2",
            "declaration": "goto_10",
            "var_declaration": "goto_6",
            "type_specifier": "goto_7",
            "fun_declaration": "goto_8",
            "$": "reduce_1"
        },
        "5": {
            "void": "reduce_3",
            "int": "reduce_3",
            "$": "reduce_3"
        },
        "6": {
            "void": "reduce_4",
            "int": "reduce_4",
            "$": "reduce_4"
        },
        "7": {
            "declare_id": "goto_11",
            "ID": "reduce_75"
        },
        "8": {
            "void": "reduce_5",
            "int": "reduce_5",
            "$": "reduce_5"
        },
        "9": {
            "$": "accept"
        },
        "10": {
            "void": "reduce_2",
            "int": "reduce_2",
            "$": "reduce_2"
        },
        "11": {
            "pid": "goto_12",
            "ID": "reduce_74"
        },
        "12": {
            "ID": "shift_13"
        },
        "13": {
            ";": "shift_14",
            "[": "shift_15",
            "(": "shift_16"
        },
        "14": {
            "NUM": "reduce_6",
            "$": "reduce_6",
            ";": "reduce_6",
            "(": "reduce_6",
            "return": "reduce_6",
            "void": "reduce_6",
            "int": "reduce_6",
            "while": "reduce_6",
            "{": "reduce_6",
            "}": "reduce_6",
            "break": "reduce_6",
            "ID": "reduce_6",
            "if": "reduce_6",
            "switch": "reduce_6"
        },
        "15": {
            "NUM": "shift_17"
        },
        "16": {
            "int": "shift_1",
            "void": "shift_18",
            "type_specifier": "goto_19",
            "params": "goto_20",
            "param_list": "goto_21",
            "param": "goto_22"
        },
        "17": {
            "]": "shift_23"
        },
        "18": {
            ")": "reduce_12",
            "ID": "reduce_9"
        },
        "19": {
            "declare_id": "goto_24",
            "ID": "reduce_75"
        },
        "20": {
            ")": "shift_25"
        },
        "21": {
            ",": "shift_26",
            ")": "reduce_11"
        },
        "22": {
            ",": "reduce_14",
            ")": "reduce_14"
        },
        "23": {
            ";": "shift_27"
        },
        "24": {
            "pid": "goto_28",
            "ID": "reduce_74"
        },
        "25": {
            "end_declare": "goto_29",
            "{": "reduce_76"
        },
        "26": {
            "int": "shift_1",
            "void": "shift_2",
            "type_specifier": "goto_19",
            "param": "goto_30"
        },
        "27": {
            "NUM": "reduce_7",
            "$": "reduce_7",
            ";": "reduce_7",
            "(": "reduce_7",
            "return": "reduce_7",
            "void": "reduce_7",
            "int": "reduce_7",
            "while": "reduce_7",
            "{": "reduce_7",
            "}": "reduce_7",
            "break": "reduce_7",
            "ID": "reduce_7",
            "if": "reduce_7",
            "switch": "reduce_7"
        },
        "28": {
            "ID": "shift_31"
        },
        "29": {
            "{": "shift_32",
            "compound_stmt": "goto_33"
        },
        "30": {
            ",": "reduce_13",
            ")": "reduce_13"
        },
        "31": {
            "[": "shift_34",
            ",": "reduce_15",
            ")": "reduce_15"
        },
        "32": {
            "local_declarations": "goto_35",
            "NUM": "reduce_19",
            ";": "reduce_19",
            "(": "reduce_19",
            "return": "reduce_19",
            "void": "reduce_19",
            "int": "reduce_19",
            "while": "reduce_19",
            "{": "reduce_19",
            "}": "reduce_19",
            "break": "reduce_19",
            "ID": "reduce_19",
            "if": "reduce_19",
            "switch": "reduce_19"
        },
        "33": {
            "void": "reduce_10",
            "int": "reduce_10",
            "$": "reduce_10"
        },
        "34": {
            "]": "shift_36"
        },
        "35": {
            "int": "shift_1",
            "void": "shift_2",
            "var_declaration": "goto_37",
            "type_specifier": "goto_38",
            "statement_list": "goto_39",
            "NUM": "reduce_21",
            ";": "reduce_21",
            "(": "reduce_21",
            "return": "reduce_21",
            "while": "reduce_21",
            "default": "reduce_21",
            "{": "reduce_21",
            "}": "reduce_21",
            "break": "reduce_21",
            "ID": "reduce_21",
            "if": "reduce_21",
            "switch": "reduce_21",
            "case": "reduce_21"
        },
        "36": {
            ",": "reduce_16",
            ")": "reduce_16"
        },
        "37": {
            "NUM": "reduce_18",
            ";": "reduce_18",
            "(": "reduce_18",
            "return": "reduce_18",
            "void": "reduce_18",
            "int": "reduce_18",
            "while": "reduce_18",
            "{": "reduce_18",
            "}": "reduce_18",
            "break": "reduce_18",
            "ID": "reduce_18",
            "if": "reduce_18",
            "switch": "reduce_18"
        },
        "38": {
            "declare_id": "goto_40",
            "ID": "reduce_75"
        },
        "39": {
            ";": "shift_41",
            "(": "reduce_73",
            "{": "shift_32",
            "}": "shift_43",
            "break": "shift_44",
            "if": "shift_45",
            "while": "shift_46",
            "return": "shift_47",
            "compound_stmt": "goto_48",
            "statement": "goto_49",
            "expression_stmt": "goto_50",
            "selection_stmt": "goto_51",
            "iteration_stmt": "goto_52",
            "return_stmt": "goto_53",
            "switch_stmt": "goto_54",
            "expression": "goto_55",
            "var": "goto_56",
            "simple_expression": "goto_57",
            "additive_expression": "goto_58",
            "term": "goto_59",
            "factor": "goto_60",
            "call": "goto_61",
            "switch": "reduce_73",
            "declare_id": "goto_63",
            "num": "goto_64",
            "NUM": "reduce_78",
            "ID": "reduce_75"
        },
        "40": {
            "pid": "goto_65",
            "ID": "reduce_74"
        },
        "41": {
            "NUM": "reduce_30",
            ";": "reduce_30",
            "(": "reduce_30",
            "return": "reduce_30",
            "while": "reduce_30",
            "else": "reduce_30",
            "default": "reduce_30",
            "{": "reduce_30",
            "}": "reduce_30",
            "endif": "reduce_30",
            "break": "reduce_30",
            "ID": "reduce_30",
            "if": "reduce_30",
            "switch": "reduce_30",
            "case": "reduce_30"
        },
        "42": {
            "(": "shift_42",
            "expression": "goto_66",
            "var": "goto_56",
            "simple_expression": "goto_57",
            "additive_expression": "goto_58",
            "term": "goto_59",
            "factor": "goto_60",
            "call": "goto_61",
            "declare_id": "goto_63",
            "num": "goto_64",
            "NUM": "reduce_78",
            "ID": "reduce_75"
        },
        "43": {
            "NUM": "reduce_17",
            "$": "reduce_17",
            ";": "reduce_17",
            "(": "reduce_17",
            "return": "reduce_17",
            "void": "reduce_17",
            "int": "reduce_17",
            "while": "reduce_17",
            "else": "reduce_17",
            "default": "reduce_17",
            "{": "reduce_17",
            "}": "reduce_17",
            "endif": "reduce_17",
            "break": "reduce_17",
            "ID": "reduce_17",
            "if": "reduce_17",
            "switch": "reduce_17",
            "case": "reduce_17"
        },
        "44": {
            ";": "shift_67"
        },
        "45": {
            "(": "shift_68"
        },
        "46": {
            "label": "goto_69",
            "(": "reduce_72"
        },
        "47": {
            ";": "shift_70",
            "(": "shift_42",
            "expression": "goto_71",
            "var": "goto_56",
            "simple_expression": "goto_57",
            "additive_expression": "goto_58",
            "term": "goto_59",
            "factor": "goto_60",
            "call": "goto_61",
            "declare_id": "goto_63",
            "num": "goto_64",
            "NUM": "reduce_78",
            "ID": "reduce_75"
        },
        "48": {
            "NUM": "reduce_23",
            ";": "reduce_23",
            "(": "reduce_23",
            "return": "reduce_23",
            "while": "reduce_23",
            "else": "reduce_23",
            "default": "reduce_23",
            "{": "reduce_23",
            "}": "reduce_23",
            "endif": "reduce_23",
            "break": "reduce_23",
            "ID": "reduce_23",
            "if": "reduce_23",
            "switch": "reduce_23",
            "case": "reduce_23"
        },
        "49": {
            "NUM": "reduce_20",
            ";": "reduce_20",
            "(": "reduce_20",
            "return": "reduce_20",
            "while": "reduce_20",
            "default": "reduce_20",
            "{": "reduce_20",
            "}": "reduce_20",
            "break": "reduce_20",
            "ID": "reduce_20",
            "if": "reduce_20",
            "switch": "reduce_20",
            "case": "reduce_20"
        },
        "50": {
            "NUM": "reduce_22",
            ";": "reduce_22",
            "(": "reduce_22",
            "return": "reduce_22",
            "while": "reduce_22",
            "else": "reduce_22",
            "default": "reduce_22",
            "{": "reduce_22",
            "}": "reduce_22",
            "endif": "reduce_22",
            "break": "reduce_22",
            "ID": "reduce_22",
            "if": "reduce_22",
            "switch": "reduce_22",
            "case": "reduce_22"
        },
        "51": {
            "NUM": "reduce_24",
            ";": "reduce_24",
            "(": "reduce_24",
            "return": "reduce_24",
            "while": "reduce_24",
            "else": "reduce_24",
            "default": "reduce_24",
            "{": "reduce_24",
            "}": "reduce_24",
            "endif": "reduce_24",
            "break": "reduce_24",
            "ID": "reduce_24",
            "if": "reduce_24",
            "switch": "reduce_24",
            "case": "reduce_24"
        },
        "52": {
            "NUM": "reduce_25",
            ";": "reduce_25",
            "(": "reduce_25",
            "return": "reduce_25",
            "while": "reduce_25",
            "else": "reduce_25",
            "default": "reduce_25",
            "{": "reduce_25",
            "}": "reduce_25",
            "endif": "reduce_25",
            "break": "reduce_25",
            "ID": "reduce_25",
            "if": "reduce_25",
            "switch": "reduce_25",
            "case": "reduce_25"
        },
        "53": {
            "NUM": "reduce_26",
            ";": "reduce_26",
            "(": "reduce_26",
            "return": "reduce_26",
            "while": "reduce_26",
            "else": "reduce_26",
            "default": "reduce_26",
            "{": "reduce_26",
            "}": "reduce_26",
            "endif": "reduce_26",
            "break": "reduce_26",
            "ID": "reduce_26",
            "if": "reduce_26",
            "switch": "reduce_26",
            "case": "reduce_26"
        },
        "54": {
            "NUM": "reduce_27",
            ";": "reduce_27",
            "(": "reduce_27",
            "return": "reduce_27",
            "while": "reduce_27",
            "else": "reduce_27",
            "default": "reduce_27",
            "{": "reduce_27",
            "}": "reduce_27",
            "endif": "reduce_27",
            "break": "reduce_27",
            "ID": "reduce_27",
            "if": "reduce_27",
            "switch": "reduce_27",
            "case": "reduce_27"
        },
        "55": {
            ";": "shift_72"
        },
        "56": {
            "=": "shift_73",
            "+": "reduce_59",
            ")": "reduce_59",
            "-": "reduce_59",
            ";": "reduce_59",
            "<": "reduce_59",
            "*": "reduce_59",
            ",": "reduce_59",
            "==": "reduce_59",
            "/": "reduce_59",
            "]": "reduce_59"
        },
        "57": {
            ")": "reduce_43",
            "]": "reduce_43",
            ",": "reduce_43",
            ";": "reduce_43"
        },
        "58": {
            "<": "shift_74",
            "==": "shift_75",
            "relop": "goto_76",
            "addop": "goto_77",
            "op": "goto_78",
            "+": "reduce_77",
            "-": "reduce_77",
            "/": "reduce_77",
            "*": "reduce_77",
            ")": "reduce_47",
            "]": "reduce_47",
            ",": "reduce_47",
            ";": "reduce_47"
        },
        "59": {
            "mulop": "goto_79",
            "op": "goto_80",
            "+": "reduce_51",
            "-": "reduce_51",
            "/": "reduce_77",
            "*": "reduce_77",
            ")": "reduce_51",
            "<": "reduce_51",
            ";": "reduce_51",
            "]": "reduce_51",
            ",": "reduce_51",
            "==": "reduce_51"
        },
        "60": {
            "+": "reduce_55",
            "*": "reduce_55",
            ")": "reduce_55",
            "-": "reduce_55",
            "/": "reduce_55",
            ";": "reduce_55",
            "<": "reduce_55",
            "]": "reduce_55",
            ",": "reduce_55",
            "==": "reduce_55"
        },
        "61": {
            "+": "reduce_60",
            ")": "reduce_60",
            "-": "reduce_60",
            ";": "reduce_60",
            "<": "reduce_60",
            "*": "reduce_60",
            ",": "reduce_60",
            "==": "reduce_60",
            "/": "reduce_60",
            "]": "reduce_60"
        },
        "62": {
            "switch": "shift_81"
        },
        "63": {
            "pid": "goto_82",
            "ID": "reduce_74"
        },
        "64": {
            "NUM": "shift_83"
        },
        "65": {
            "ID": "shift_84"
        },
        "66": {
            ")": "shift_85"
        },
        "67": {
            "NUM": "reduce_29",
            ";": "reduce_29",
            "(": "reduce_29",
            "return": "reduce_29",
            "while": "reduce_29",
            "else": "reduce_29",
            "default": "reduce_29",
            "{": "reduce_29",
            "}": "reduce_29",
            "endif": "reduce_29",
            "break": "reduce_29",
            "ID": "reduce_29",
            "if": "reduce_29",
            "switch": "reduce_29",
            "case": "reduce_29"
        },
        "68": {
            "(": "shift_42",
            "expression": "goto_86",
            "var": "goto_56",
            "simple_expression": "goto_57",
            "additive_expression": "goto_58",
            "term": "goto_59",
            "factor": "goto_60",
            "call": "goto_61",
            "declare_id": "goto_63",
            "num": "goto_64",
            "NUM": "reduce_78",
            "ID": "reduce_75"
        },
        "69": {
            "(": "shift_87"
        },
        "70": {
            "NUM": "reduce_34",
            ";": "reduce_34",
            "(": "reduce_34",
            "return": "reduce_34",
            "while": "reduce_34",
            "else": "reduce_34",
            "default": "reduce_34",
            "{": "reduce_34",
            "}": "reduce_34",
            "endif": "reduce_34",
            "break": "reduce_34",
            "ID": "reduce_34",
            "if": "reduce_34",
            "switch": "reduce_34",
            "case": "reduce_34"
        },
        "71": {
            ";": "shift_88"
        },
        "72": {
            "NUM": "reduce_28",
            ";": "reduce_28",
            "(": "reduce_28",
            "return": "reduce_28",
            "while": "reduce_28",
            "else": "reduce_28",
            "default": "reduce_28",
            "{": "reduce_28",
            "}": "reduce_28",
            "endif": "reduce_28",
            "break": "reduce_28",
            "ID": "reduce_28",
            "if": "reduce_28",
            "switch": "reduce_28",
            "case": "reduce_28"
        },
        "73": {
            "(": "shift_42",
            "expression": "goto_89",
            "var": "goto_56",
            "simple_expression": "goto_57",
            "additive_expression": "goto_58",
            "term": "goto_59",
            "factor": "goto_60",
            "call": "goto_61",
            "declare_id": "goto_63",
            "num": "goto_64",
            "NUM": "reduce_78",
            "ID": "reduce_75"
        },
        "74": {
            "NUM": "reduce_48",
            "ID": "reduce_48",
            "(": "reduce_48"
        },
        "75": {
            "NUM": "reduce_49",
            "ID": "reduce_49",
            "(": "reduce_49"
        },
        "76": {
            "(": "shift_42",
            "var": "goto_90",
            "additive_expression": "goto_91",
            "term": "goto_59",
            "factor": "goto_60",
            "call": "goto_61",
            "declare_id": "goto_63",
            "num": "goto_64",
            "NUM": "reduce_78",
            "ID": "reduce_75"
        },
        "77": {
            "(": "shift_42",
            "var": "goto_90",
            "term": "goto_92",
            "factor": "goto_60",
            "call": "goto_61",
            "declare_id": "goto_63",
            "num": "goto_64",
            "NUM": "reduce_78",
            "ID": "reduce_75"
        },
        "78": {
            "+": "shift_93",
            "-": "shift_94"
        },
        "79": {
            "(": "shift_42",
            "var": "goto_90",
            "factor": "goto_95",
            "call": "goto_61",
            "declare_id": "goto_63",
            "num": "goto_64",
            "NUM": "reduce_78",
            "ID": "reduce_75"
        },
        "80": {
            "*": "shift_96",
            "/": "shift_97"
        },
        "81": {
            "(": "shift_98"
        },
        "82": {
            "ID": "shift_99"
        },
        "83": {
            "+": "reduce_61",
            ")": "reduce_61",
            "-": "reduce_61",
            ";": "reduce_61",
            "<": "reduce_61",
            "*": "reduce_61",
            ",": "reduce_61",
            "==": "reduce_61",
            "/": "reduce_61",
            "]": "reduce_61"
        },
        "84": {
            ";": "shift_14",
            "[": "shift_15"
        },
        "85": {
            "+": "reduce_58",
            ")": "reduce_58",
            "-": "reduce_58",
            ";": "reduce_58",
            "<": "reduce_58",
            "*": "reduce_58",
            ",": "reduce_58",
            "==": "reduce_58",
            "/": "reduce_58",
            "]": "reduce_58"
        },
        "86": {
            ")": "shift_100"
        },
        "87": {
            "(": "shift_42",
            "expression": "goto_101",
            "var": "goto_56",
            "simple_expression": "goto_57",
            "additive_expression": "goto_58",
            "term": "goto_59",
            "factor": "goto_60",
            "call": "goto_61",
            "declare_id": "goto_63",
            "num": "goto_64",
            "NUM": "reduce_78",
            "ID": "reduce_75"
        },
        "88": {
            "NUM": "reduce_35",
            ";": "reduce_35",
            "(": "reduce_35",
            "return": "reduce_35",
            "while": "reduce_35",
            "else": "reduce_35",
            "default": "reduce_35",
            "{": "reduce_35",
            "}": "reduce_35",
            "endif": "reduce_35",
            "break": "reduce_35",
            "ID": "reduce_35",
            "if": "reduce_35",
            "switch": "reduce_35",
            "case": "reduce_35"
        },
        "89": {
            ")": "reduce_42",
            "]": "reduce_42",
            ",": "reduce_42",
            ";": "reduce_42"
        },
        "90": {
            "+": "reduce_59",
            ")": "reduce_59",
            "-": "reduce_59",
            ";": "reduce_59",
            "<": "reduce_59",
            "*": "reduce_59",
            ",": "reduce_59",
            "==": "reduce_59",
            "/": "reduce_59",
            "]": "reduce_59"
        },
        "91": {
            "addop": "goto_77",
            "op": "goto_78",
            "+": "reduce_77",
            "-": "reduce_77",
            "/": "reduce_77",
            "*": "reduce_77",
            ")": "reduce_46",
            "]": "reduce_46",
            ",": "reduce_46",
            ";": "reduce_46"
        },
        "92": {
            "mulop": "goto_79",
            "op": "goto_80",
            "+": "reduce_50",
            "-": "reduce_50",
            "/": "reduce_77",
            "*": "reduce_77",
            ")": "reduce_50",
            "<": "reduce_50",
            ";": "reduce_50",
            "]": "reduce_50",
            ",": "reduce_50",
            "==": "reduce_50"
        },
        "93": {
            "NUM": "reduce_52",
            "ID": "reduce_52",
            "(": "reduce_52"
        },
        "94": {
            "NUM": "reduce_53",
            "ID": "reduce_53",
            "(": "reduce_53"
        },
        "95": {
            "+": "reduce_54",
            "*": "reduce_54",
            ")": "reduce_54",
            "-": "reduce_54",
            "/": "reduce_54",
            ";": "reduce_54",
            "<": "reduce_54",
            "]": "reduce_54",
            ",": "reduce_54",
            "==": "reduce_54"
        },
        "96": {
            "NUM": "reduce_56",
            "ID": "reduce_56",
            "(": "reduce_56"
        },
        "97": {
            "NUM": "reduce_57",
            "ID": "reduce_57",
            "(": "reduce_57"
        },
        "98": {
            "(": "shift_42",
            "expression": "goto_102",
            "var": "goto_56",
            "simple_expression": "goto_57",
            "additive_expression": "goto_58",
            "term": "goto_59",
            "factor": "goto_60",
            "call": "goto_61",
            "declare_id": "goto_63",
            "num": "goto_64",
            "NUM": "reduce_78",
            "ID": "reduce_75"
        },
        "99": {
            "[": "shift_103",
            "(": "shift_104",
            "+": "reduce_44",
            ")": "reduce_44",
            "-": "reduce_44",
            ";": "reduce_44",
            "<": "reduce_44",
            "*": "reduce_44",
            ",": "reduce_44",
            "==": "reduce_44",
            "=": "reduce_44",
            "/": "reduce_44",
            "]": "reduce_44"
        },
        "100": {
            "save": "goto_105",
            "NUM": "reduce_70",
            ";": "reduce_70",
            ":": "reduce_70",
            "(": "reduce_70",
            "return": "reduce_70",
            "while": "reduce_70",
            "{": "reduce_70",
            "break": "reduce_70",
            "ID": "reduce_70",
            "if": "reduce_70",
            "switch": "reduce_70"
        },
        "101": {
            ")": "shift_106"
        },
        "102": {
            ")": "shift_107"
        },
        "103": {
            "(": "shift_42",
            "expression": "goto_108",
            "var": "goto_56",
            "simple_expression": "goto_57",
            "additive_expression": "goto_58",
            "term": "goto_59",
            "factor": "goto_60",
            "call": "goto_61",
            "declare_id": "goto_63",
            "num": "goto_64",
            "NUM": "reduce_78",
            "ID": "reduce_75"
        },
        "104": {
            "add_args": "goto_109",
            ")": "reduce_63",
            "NUM": "reduce_63",
            "ID": "reduce_63",
            "(": "reduce_63"
        },
        "105": {
            ";": "shift_41",
            "(": "reduce_73",
            "{": "shift_32",
            "break": "shift_44",
            "if": "shift_45",
            "while": "shift_46",
            "return": "shift_47",
            "compound_stmt": "goto_48",
            "statement": "goto_110",
            "expression_stmt": "goto_50",
            "selection_stmt": "goto_51",
            "iteration_stmt": "goto_52",
            "return_stmt": "goto_53",
            "switch_stmt": "goto_54",
            "expression": "goto_55",
            "var": "goto_56",
            "simple_expression": "goto_57",
            "additive_expression": "goto_58",
            "term": "goto_59",
            "factor": "goto_60",
            "call": "goto_61",
            "switch": "reduce_73",
            "declare_id": "goto_63",
            "num": "goto_64",
            "NUM": "reduce_78",
            "ID": "reduce_75"
        },
        "106": {
            "save": "goto_111",
            "NUM": "reduce_70",
            ";": "reduce_70",
            ":": "reduce_70",
            "(": "reduce_70",
            "return": "reduce_70",
            "while": "reduce_70",
            "{": "reduce_70",
            "break": "reduce_70",
            "ID": "reduce_70",
            "if": "reduce_70",
            "switch": "reduce_70"
        },
        "107": {
            "{": "shift_112"
        },
        "108": {
            "]": "shift_113"
        },
        "109": {
            "(": "shift_42",
            "expression": "goto_114",
            "var": "goto_56",
            "simple_expression": "goto_57",
            "additive_expression": "goto_58",
            "term": "goto_59",
            "factor": "goto_60",
            "call": "goto_61",
            "args": "goto_115",
            "arg_list": "goto_116",
            "declare_id": "goto_63",
            "num": "goto_64",
            "NUM": "reduce_78",
            "ID": "reduce_75",
            ")": "reduce_67"
        },
        "110": {
            "endif": "shift_117",
            "else": "shift_118"
        },
        "111": {
            ";": "shift_41",
            "(": "reduce_73",
            "{": "shift_32",
            "break": "shift_44",
            "if": "shift_45",
            "while": "shift_46",
            "return": "shift_47",
            "compound_stmt": "goto_48",
            "statement": "goto_119",
            "expression_stmt": "goto_50",
            "selection_stmt": "goto_51",
            "iteration_stmt": "goto_52",
            "return_stmt": "goto_53",
            "switch_stmt": "goto_54",
            "expression": "goto_55",
            "var": "goto_56",
            "simple_expression": "goto_57",
            "additive_expression": "goto_58",
            "term": "goto_59",
            "factor": "goto_60",
            "call": "goto_61",
            "switch": "reduce_73",
            "declare_id": "goto_63",
            "num": "goto_64",
            "NUM": "reduce_78",
            "ID": "reduce_75"
        },
        "112": {
            "case_stmts": "goto_120",
            "}": "reduce_38",
            "default": "reduce_38",
            "case": "reduce_38"
        },
        "113": {
            "+": "reduce_45",
            ")": "reduce_45",
            "-": "reduce_45",
            ";": "reduce_45",
            "<": "reduce_45",
            "*": "reduce_45",
            ",": "reduce_45",
            "==": "reduce_45",
            "=": "reduce_45",
            "/": "reduce_45",
            "]": "reduce_45"
        },
        "114": {
            ",": "reduce_69",
            ")": "reduce_69"
        },
        "115": {
            ")": "shift_121"
        },
        "116": {
            ",": "shift_122",
            ")": "reduce_66"
        },
        "117": {
            "NUM": "reduce_31",
            ";": "reduce_31",
            "(": "reduce_31",
            "return": "reduce_31",
            "while": "reduce_31",
            "else": "reduce_31",
            "default": "reduce_31",
            "{": "reduce_31",
            "}": "reduce_31",
            "endif": "reduce_31",
            "break": "reduce_31",
            "ID": "reduce_31",
            "if": "reduce_31",
            "switch": "reduce_31",
            "case": "reduce_31"
        },
        "118": {
            "jpf_save": "goto_123",
            "NUM": "reduce_71",
            ";": "reduce_71",
            "(": "reduce_71",
            "return": "reduce_71",
            "while": "reduce_71",
            "default": "reduce_71",
            "{": "reduce_71",
            "break": "reduce_71",
            "ID": "reduce_71",
            "if": "reduce_71",
            "switch": "reduce_71",
            "case": "reduce_71"
        },
        "119": {
            "NUM": "reduce_33",
            ";": "reduce_33",
            "(": "reduce_33",
            "return": "reduce_33",
            "while": "reduce_33",
            "else": "reduce_33",
            "default": "reduce_33",
            "{": "reduce_33",
            "}": "reduce_33",
            "endif": "reduce_33",
            "break": "reduce_33",
            "ID": "reduce_33",
            "if": "reduce_33",
            "switch": "reduce_33",
            "case": "reduce_33"
        },
        "120": {
            "case_stmt": "goto_124",
            "default_stmt": "goto_125",
            "jpf_save": "goto_126",
            "}": "reduce_41",
            "NUM": "reduce_71",
            ";": "reduce_71",
            "(": "reduce_71",
            "return": "reduce_71",
            "while": "reduce_71",
            "default": "reduce_71",
            "{": "reduce_71",
            "break": "reduce_71",
            "ID": "reduce_71",
            "if": "reduce_71",
            "switch": "reduce_71",
            "case": "reduce_71"
        },
        "121": {
            "end_args": "goto_127",
            "+": "reduce_65",
            ")": "reduce_65",
            "-": "reduce_65",
            "<": "reduce_65",
            ";": "reduce_65",
            "*": "reduce_65",
            ",": "reduce_65",
            "==": "reduce_65",
            "/": "reduce_65",
            "]": "reduce_65"
        },
        "122": {
            "(": "shift_42",
            "expression": "goto_128",
            "var": "goto_56",
            "simple_expression": "goto_57",
            "additive_expression": "goto_58",
            "term": "goto_59",
            "factor": "goto_60",
            "call": "goto_61",
            "declare_id": "goto_63",
            "num": "goto_64",
            "NUM": "reduce_78",
            "ID": "reduce_75"
        },
        "123": {
            ";": "shift_41",
            "(": "reduce_73",
            "{": "shift_32",
            "break": "shift_44",
            "if": "shift_45",
            "while": "shift_46",
            "return": "shift_47",
            "compound_stmt": "goto_48",
            "statement": "goto_129",
            "expression_stmt": "goto_50",
            "selection_stmt": "goto_51",
            "iteration_stmt": "goto_52",
            "return_stmt": "goto_53",
            "switch_stmt": "goto_54",
            "expression": "goto_55",
            "var": "goto_56",
            "simple_expression": "goto_57",
            "additive_expression": "goto_58",
            "term": "goto_59",
            "factor": "goto_60",
            "call": "goto_61",
            "switch": "reduce_73",
            "declare_id": "goto_63",
            "num": "goto_64",
            "NUM": "reduce_78",
            "ID": "reduce_75"
        },
        "124": {
            "}": "reduce_37",
            "default": "reduce_37",
            "case": "reduce_37"
        },
        "125": {
            "}": "shift_130"
        },
        "126": {
            "case": "shift_131",
            "default": "shift_132"
        },
        "127": {
            "print": "goto_133",
            "+": "reduce_64",
            ")": "reduce_64",
            "-": "reduce_64",
            ";": "reduce_64",
            "<": "reduce_64",
            "*": "reduce_64",
            ",": "reduce_64",
            "==": "reduce_64",
            "/": "reduce_64",
            "]": "reduce_64"
        },
        "128": {
            ",": "reduce_68",
            ")": "reduce_68"
        },
        "129": {
            "endif": "shift_134"
        },
        "130": {
            "NUM": "reduce_36",
            ";": "reduce_36",
            "(": "reduce_36",
            "return": "reduce_36",
            "while": "reduce_36",
            "else": "reduce_36",
            "default": "reduce_36",
            "{": "reduce_36",
            "}": "reduce_36",
            "endif": "reduce_36",
            "break": "reduce_36",
            "ID": "reduce_36",
            "if": "reduce_36",
            "switch": "reduce_36",
            "case": "reduce_36"
        },
        "131": {
            "NUM": "shift_135"
        },
        "132": {
            ":": "shift_136"
        },
        "133": {
            "+": "reduce_62",
            ")": "reduce_62",
            "-": "reduce_62",
            ";": "reduce_62",
            "<": "reduce_62",
            "*": "reduce_62",
            ",": "reduce_62",
            "==": "reduce_62",
            "/": "reduce_62",
            "]": "reduce_62"
        },
        "134": {
            "NUM": "reduce_32",
            ";": "reduce_32",
            "(": "reduce_32",
            "return": "reduce_32",
            "while": "reduce_32",
            "else": "reduce_32",
            "default": "reduce_32",
            "{": "reduce_32",
            "}": "reduce_32",
            "endif": "reduce_32",
            "break": "reduce_32",
            "ID": "reduce_32",
            "if": "reduce_32",
            "switch": "reduce_32",
            "case": "reduce_32"
        },
        "135": {
            "save": "goto_137",
            "NUM": "reduce_70",
            ";": "reduce_70",
            ":": "reduce_70",
            "(": "reduce_70",
            "return": "reduce_70",
            "while": "reduce_70",
            "{": "reduce_70",
            "break": "reduce_70",
            "ID": "reduce_70",
            "if": "reduce_70",
            "switch": "reduce_70"
        },
        "136": {
            "statement_list": "goto_138",
            "NUM": "reduce_21",
            ";": "reduce_21",
            "(": "reduce_21",
            "return": "reduce_21",
            "while": "reduce_21",
            "default": "reduce_21",
            "{": "reduce_21",
            "}": "reduce_21",
            "break": "reduce_21",
            "ID": "reduce_21",
            "if": "reduce_21",
            "switch": "reduce_21",
            "case": "reduce_21"
        },
        "137": {
            ":": "shift_139"
        },
        "138": {
            ";": "shift_41",
            "(": "reduce_73",
            "{": "shift_32",
            "break": "shift_44",
            "if": "shift_45",
            "while": "shift_46",
            "return": "shift_47",
            "compound_stmt": "goto_48",
            "statement": "goto_49",
            "expression_stmt": "goto_50",
            "selection_stmt": "goto_51",
            "iteration_stmt": "goto_52",
            "return_stmt": "goto_53",
            "switch_stmt": "goto_54",
            "expression": "goto_55",
            "var": "goto_56",
            "simple_expression": "goto_57",
            "additive_expression": "goto_58",
            "term": "goto_59",
            "factor": "goto_60",
            "call": "goto_61",
            "switch": "reduce_73",
            "declare_id": "goto_63",
            "num": "goto_64",
            "NUM": "reduce_78",
            "ID": "reduce_75",
            "}": "reduce_40"
        },
        "139": {
            "statement_list": "goto_140",
            "NUM": "reduce_21",
            ";": "reduce_21",
            "(": "reduce_21",
            "return": "reduce_21",
            "while": "reduce_21",
            "default": "reduce_21",
            "{": "reduce_21",
            "}": "reduce_21",
            "break": "reduce_21",
            "ID": "reduce_21",
            "if": "reduce_21",
            "switch": "reduce_21",
            "case": "reduce_21"
        },
        "140": {
            ";": "shift_41",
            "(": "reduce_73",
            "{": "shift_32",
            "break": "shift_44",
            "if": "shift_45",
            "while": "shift_46",
            "return": "shift_47",
            "compound_stmt": "goto_48",
            "statement": "goto_49",
            "expression_stmt": "goto_50",
            "selection_stmt": "goto_51",
            "iteration_stmt": "goto_52",
            "return_stmt": "goto_53",
            "switch_stmt": "goto_54",
            "expression": "goto_55",
            "var": "goto_56",
            "simple_expression": "goto_57",
            "additive_expression": "goto_58",
            "term": "goto_59",
            "factor": "goto_60",
            "call": "goto_61",
            "switch": "reduce_73",
            "declare_id": "goto_63",
            "num": "goto_64",
            "NUM": "reduce_78",
            "ID": "reduce_75",
            "}": "reduce_39",
            "default": "reduce_39",
            "case": "reduce_39"
        }
    }
}